badges_gitlab/__init__.py
badges_gitlab/badges_api.py
badges_gitlab/badges_json.py
badges_gitlab/badges_static.py
badges_gitlab/badges_svg.py
badges_gitlab/badges_test.py
badges_gitlab/cli.py
badges_gitlab/read_pyproject.py
badges_gitlab-1.0.2.dist-info/LICENSE
badges_gitlab-1.0.2.dist-info/METADATA
badges_gitlab-1.0.2.dist-info/WHEEL
badges_gitlab-1.0.2.dist-info/entry_points.txt
badges_gitlab-1.0.2.dist-info/RECORD
