Metadata-Version: 2.1
Name: badges-gitlab
Version: 1.0.2
Summary: Generate badges for Gitlab Projects in Public and Private Repositories
License: MIT
Author: Felipe P. Silva
Author-email: felipefoz@gmail.com
Requires-Python: >=3.8.1,<4.0.0
Classifier: Development Status :: 5 - Production/Stable
Classifier: Intended Audience :: Developers
Classifier: License :: OSI Approved :: MIT License
Classifier: Operating System :: OS Independent
Classifier: Programming Language :: Python :: 3
Classifier: Programming Language :: Python :: 3.9
Classifier: Programming Language :: Python :: 3.10
Classifier: Programming Language :: Python :: 3.11
Classifier: Programming Language :: Python :: 3.12
Classifier: Programming Language :: Python :: 3.13
Classifier: Programming Language :: Python :: 3.8
Requires-Dist: anybadge (>=1.14.0,<2.0.0)
Requires-Dist: iso8601 (>=2.1.0,<3.0.0)
Requires-Dist: junitparser (>=3.1.0,<4.0.0)
Requires-Dist: python-gitlab (==3.15)
Requires-Dist: requests (>=2.31.0,<3.0.0)
Requires-Dist: toml (>=0.10.2,<0.11.0)
Requires-Dist: xmltodict (>=0.14.0,<0.15.0)
Project-URL: Bug Tracker, https://gitlab.com/felipe_public/badges-gitlab/-/issues
Project-URL: documentation, https://badges-gitlab.readthedocs.io
Project-URL: homepage, https://gitlab.com/felipe_public/badges-gitlab
Project-URL: repository, https://gitlab.com/felipe_public/badges-gitlab
